uphill/VERSION
uphill/__init__.py
uphill/errors.py
uphill/logx.py
uphill/apply/__init__.py
uphill/apply/aishell.py
uphill/apply/aishell2.py
uphill/apply/musan.py
uphill/array/__init__.py
uphill/array/document_array.py
uphill/array/supervision_array.py
uphill/array/mixins/__init__.py
uphill/array/mixins/algorithm.py
uphill/array/mixins/auto_compress.py
uphill/array/mixins/serialization.py
uphill/bin/__init__.py
uphill/bin/download.py
uphill/bin/main.py
uphill/bin/parser.py
uphill/bin/parser_base.py
uphill/bin/prepare.py
uphill/core/__init__.py
uphill/core/audio/__init__.py
uphill/core/audio/augment.py
uphill/core/audio/io.py
uphill/core/audio/utils.py
uphill/core/text/__init__.py
uphill/core/text/lang.model
uphill/core/text/own_langid.py
uphill/core/text/utils.py
uphill/core/text/vocab.py
uphill/core/utils/__init__.py
uphill/core/utils/constant.py
uphill/core/utils/download.py
uphill/core/utils/io.py
uphill/core/utils/module.py
uphill/core/utils/parallel.py
uphill/core/utils/timing.py
uphill/core/utils/typing.py
uphill/document/__init__.py
uphill/document/document.py
uphill/document/helper.py
uphill/document/source.py
uphill/document/supervision.py
uphill/document/mixins/__init__.py
uphill/document/mixins/internal.py
uphill/document/mixins/plot.py
uphill/document/mixins/serialization.py
uphill-0.1.2.dist-info/METADATA
uphill-0.1.2.dist-info/WHEEL
uphill-0.1.2.dist-info/entry_points.txt
uphill-0.1.2.dist-info/top_level.txt
uphill-0.1.2.dist-info/RECORD
