Metadata-Version: 2.1
Name: uphill
Version: 0.1.2
Summary: make data preparation more friendly
Home-page: https://github.com/yinanxu0/uphill
Author: yinanxu
Author-email: yinanxu0@gmail.com
License: UNKNOWN
Platform: UNKNOWN
Classifier: Programming Language :: Python :: 3
Classifier: Development Status :: 4 - Beta
Classifier: Intended Audience :: Developers
Classifier: Intended Audience :: Science/Research
Classifier: License :: OSI Approved :: Apache Software License
Classifier: Topic :: Scientific/Engineering :: Artificial Intelligence
Requires-Python: >=3.7
Requires-Dist: cytoolz
Requires-Dist: dill
Requires-Dist: langid
Requires-Dist: numpy
Requires-Dist: packaging
Requires-Dist: pyyaml
Requires-Dist: requests
Requires-Dist: rich
Requires-Dist: scipy
Requires-Dist: smart-open
Requires-Dist: termcolor
Requires-Dist: torch (>=1.11.0)
Requires-Dist: torchaudio (>=0.11.0)
Requires-Dist: tqdm
Requires-Dist: typeguard (==2.13.3)
Requires-Dist: typing-extensions
